releaseup/__init__.py
releaseup/extract.py
releaseup/high_level.py
releaseup/nlp_backend.py
releaseup/py.typed
releaseup/version.pyi
releaseup-0.1.1.dist-info/METADATA
releaseup-0.1.1.dist-info/WHEEL
releaseup-0.1.1.dist-info/licenses/LICENSE
releaseup-0.1.1.dist-info/RECORD
